<?xml version="1.0" encoding="utf-8"?>
    <openerp>
       <data noupdate="0">
           <!-- Creating a Group Category -->        
           <record id="suporte" model="ir.module.category">
               <field name="name">Suporte</field>
               <field name="sequence">1</field>
           </record>
           <!-- Adding a Group to the Group Category -->
           <record id="suporte.manager" model="res.groups">
               <field name="name">Suporte</field>
               <field name="category_id" ref="suporte"/>
           </record>
           
           <record id="suporte.user" model="res.groups">
               <field name="name">Usuário</field>
               <field name="category_id" ref="suporte"/>
           </record>
        </data>
    </openerp>