<?xml version='1.0' encoding='UTF-8' ?>
<openerp>
	<data>
		<record model="ir.ui.view" id="account_analytic_account_graph">
			<field name="name">account_analytic_account.graph</field>
			<field name="model">account.analytic.account</field>
			<field name="view_type">graph</field>
			<field name="priority" eval="16" />
			<field name="arch" type="xml">
				<graph string="Contratos">
					<field name="status_contrato" />
					<field name="name" />
				</graph>
			</field>
		</record>
	</data>
</openerp>